nolimit/__init__.py
nolimit/icona.png
nolimit/icona300x300.png
nolimit/icona50x50.png
nolimit/main.py
nolimit/nolimit.ui
nolimit/nolimit_sympy/__init__.py
nolimit/nolimit_sympy/nolimit_sympy.py
nolimit/nolimit_sympy/nolimit_sympy.ui
nolimit-1.0.dist-info/entry_points.txt
nolimit-1.0.dist-info/LICENSE
nolimit-1.0.dist-info/WHEEL
nolimit-1.0.dist-info/METADATA
nolimit-1.0.dist-info/RECORD
