Metadata-Version: 2.1
Name: nolimit
Version: 1.0
Summary: is a Qt5 gui to solve limits, it has two commands:
Home-page: https://github.com/Sav22999/project_nolimit_math
License: UNKNOWN
Author:  Simone Massaro (mone27), Saverio Morelli (Sav22999) 
Author-email: mone.massaro@gmail.com, saverio.morelli@outlook.it
Classifier: License :: OSI Approved :: GNU General Public License v3 or later (GPLv3+)
Requires-Dist: PyQt5
Requires-Dist: matplotlib
Requires-Dist: sympy
Requires-Dist: numpy
